pyo2.py
pyo2-0.1.3.dist-info/METADATA
pyo2-0.1.3.dist-info/WHEEL
pyo2-0.1.3.dist-info/RECORD
