Metadata-Version: 2.1
Name: pyo2
Version: 0.1.3
Summary: A lightweight method to call Rust code from Python
License: MIT
Author: david-why
Author-email: david_why@outlook.com
Requires-Python: >=3.10,<4.0
Classifier: License :: OSI Approved :: MIT License
Classifier: Programming Language :: Python :: 3
Classifier: Programming Language :: Python :: 3.10
Classifier: Programming Language :: Python :: 3.11
Classifier: Programming Language :: Python :: 3.12
